{
  "id": "phi-os.professional-deliverable-catalog",
  "version": "1.0.0",
  "milestone": "M4A-W1",
  "status": "definition-frozen-implementation-pending",
  "requiredSourceLabels": [
    "observed_runtime_evidence",
    "user_statement",
    "financial_fact",
    "document_supported",
    "system_extraction",
    "rule_inference",
    "ai_interpretation",
    "professional_calculation",
    "professional_assessment",
    "projection",
    "assumption",
    "recommendation",
    "human_design_interpretation",
    "possible_correspondence",
    "unverified_inference",
    "client_decision",
    "implementation_result"
  ],
  "profiles": [
    {
      "profileId": "automated_runtime_reading",
      "sections": [
        "Runtime Summary",
        "Observed Evidence",
        "Reconstructed Sequence",
        "Runtime Coordinates",
        "Constraints",
        "Unresolved Questions",
        "Reading Boundary"
      ]
    },
    {
      "profileId": "professional_runtime_reading",
      "sections": [
        "Runtime Summary",
        "Observed Evidence",
        "Reconstructed Sequence",
        "Runtime Coordinates",
        "Runtime Signatures",
        "Constraints",
        "Unresolved Questions",
        "Professional Revision",
        "Navigation Considerations"
      ]
    },
    {
      "profileId": "professional_consultation",
      "sections": [
        "Report Reviewed",
        "Confirmed Understanding",
        "Data Gaps",
        "Professional Observations",
        "Client Questions",
        "Client Decisions",
        "Next Review"
      ]
    },
    {
      "profileId": "navigation_follow_up",
      "sections": [
        "Previous Direction",
        "What Changed",
        "What Remained Stable",
        "New Evidence",
        "Action Result",
        "Updated Constraints",
        "Revised Direction",
        "Next Review"
      ]
    },
    {
      "profileId": "long_term_runtime_review",
      "sections": [
        "Current Runtime Position",
        "Timeline Since Previous Review",
        "Repeated Signatures",
        "Navigation Outcomes",
        "New Constraints",
        "Revision Decision",
        "Continuity Plan"
      ]
    },
    {
      "profileId": "human_design_foundation",
      "sections": [
        "Chart Overview",
        "Type and Strategy",
        "Authority",
        "Profile",
        "Definition",
        "Centers",
        "Channels",
        "Key Gates",
        "Variables / PHS",
        "General Operating Conditions",
        "Limitations and Boundary"
      ]
    },
    {
      "profileId": "human_design_runtime_interpretation",
      "sections": [
        "Runtime Carrier",
        "Decision Architecture",
        "Environmental Conditions",
        "Relational Operation",
        "Experience Style",
        "Expression Style",
        "Action Style",
        "Recurrent Signatures",
        "Current Reality Correspondence",
        "Navigation Considerations"
      ]
    },
    {
      "profileId": "reality_specific_human_design",
      "sections": [
        "Confirmed Reality Evidence",
        "Human Design Perspective",
        "Possible Correspondence",
        "Conflicting Evidence",
        "What Remains Unverified",
        "Professional Observation",
        "Navigation Considerations",
        "What to Observe Next"
      ],
      "requiredSeparatedBlocks": [
        "Confirmed Reality Evidence",
        "Human Design Perspective",
        "Possible Correspondence",
        "What Remains Unverified"
      ]
    },
    {
      "profileId": "financial_reality_snapshot",
      "sections": [
        "Financial Information Date",
        "Client and Household",
        "Financial Objectives",
        "Income Overview",
        "Expense Overview",
        "Asset Overview",
        "Liability Overview",
        "Cash Flow",
        "Net Worth",
        "Insurance Overview",
        "Investment Overview",
        "Property Overview",
        "Missing Information",
        "Missing Evidence"
      ],
      "adviceLevel": "facts-only"
    },
    {
      "profileId": "financial_stamina_analysis",
      "sections": [
        "Scope and Information Date",
        "Financial Position Summary",
        "Financial Objectives",
        "Assets and Liabilities",
        "Cash Flow",
        "Net Worth",
        "Financial Ratios",
        "Liquidity and Emergency Capacity",
        "Debt Capacity",
        "Savings Capacity",
        "Insurance Protection",
        "Investment Position",
        "Property Position",
        "Tax Considerations",
        "Retirement Readiness",
        "Education Readiness",
        "Estate Readiness",
        "Financial Hazards",
        "Navigation Priorities",
        "Assumptions and Disclaimer"
      ]
    },
    {
      "profileId": "financial_reality_consultation",
      "sections": [
        "Current Financial Position",
        "Confirmed Risks",
        "Data Gaps",
        "Financial Constraints",
        "Goal Conflicts",
        "Available Options",
        "Client Questions",
        "Client Decisions"
      ]
    },
    {
      "profileId": "financial_navigation_plan",
      "sections": [
        "Confirmed Financial Facts",
        "Professional Assessment",
        "Assumptions Used",
        "Priority Risks",
        "Recommended Direction",
        "Alternative Option",
        "Required Conditions",
        "Implementation Sequence",
        "Responsible Person",
        "Target Date",
        "Required Documents",
        "Stop or Revise Conditions",
        "Review Trigger",
        "Status"
      ]
    },
    {
      "profileId": "financial_implementation_review",
      "sections": [
        "Previous Position",
        "Updated Position",
        "Actions Completed",
        "Actions Not Completed",
        "Income and Expense Changes",
        "Asset and Liability Changes",
        "Ratio Changes",
        "New Risks",
        "Goal Progress",
        "Revised Recommendation",
        "Next Review Date"
      ]
    },
    {
      "profileId": "long_term_financial_review",
      "sections": [
        "Financial Information Date",
        "Income Changes",
        "Expense Changes",
        "Asset Changes",
        "Liability Changes",
        "Cash Flow Changes",
        "Risk Changes",
        "Household Responsibility Changes",
        "Goal Changes",
        "Implementation Results",
        "Next Scheduled Review"
      ]
    },
    {
      "profileId": "integrated_professional_review",
      "sections": [
        "Observed Runtime Evidence",
        "Financial Evidence",
        "System Calculation",
        "Professional Financial Assessment",
        "Human Design Interpretation",
        "Possible Correspondence",
        "Client Decision",
        "Implementation Result",
        "Source Separation Statement"
      ]
    }
  ]
}
